LICENSE
MANIFEST.in
README.rst
VERSION
pytest.ini
requirements.txt
setup.cfg
setup.py
onemapsg/__init__.py
onemapsg/api.py
onemapsg/client.py
onemapsg/exceptions.py
onemapsg/response.py
onemapsg/status.py
onemapsg/utils.py
python_onemapsg.egg-info/PKG-INFO
python_onemapsg.egg-info/SOURCES.txt
python_onemapsg.egg-info/dependency_links.txt
python_onemapsg.egg-info/not-zip-safe
python_onemapsg.egg-info/requires.txt
python_onemapsg.egg-info/top_level.txt
tests/__init__.py
tests/test_api.py
tests/test_client.py
tests/test_response.py
tests/test_status.py
tests/test_utils.py