Metadata-Version: 1.1
Name: python-onemapsg
Version: 0.0.5
Summary: Python Client for OneMap SG
Home-page: https://github.com/windspeed-io/python-onemapsg
Author: Thomas Jiang
Author-email: thomasjiangcy@gmail.com
License: MIT
Platform: UNKNOWN
Classifier: Programming Language :: Python :: 3.6
Classifier: Programming Language :: Python :: 3.7
Classifier: Topic :: Software Development :: Libraries :: Python Modules
